verilog/alu.v
module alu (
    input  wire [5:0]   alu_op,     // selects operation
    input  wire [31:0]  rs,         // Source register
    input  wire [31:0]  rt,         // Target register
    input  wire [15:0]  imm16,      // Immediate16
    input  wire [25:0]  target,     // Target address (for jumps)
    output reg  [31:0]  rd          // Destination register
);

    localparam ALU_ADD  = 6'h0;
    localparam ALU_SUB  = 6'h1;
    localparam ALU_AND  = 6'h2;
    localparam ALU_OR   = 6'h3;
    localparam ALU_XOR  = 6'h4;
    localparam ALU_ADDI = 6'h10;

    always @* begin
        case (alu_op)
            // Register-register operations
            ALU_ADD: rd = rs + rt;
            ALU_SUB: rd = rs - rt;
            ALU_AND: rd = rs & rt;
            ALU_OR:  rd = rs | rt;
            ALU_XOR: rd = rs ^ rt;

            // Immediate operations
            ALU_ADDI: rd = rs + {{16{imm16[15]}}, imm16};

            default: rd= 32'h0000_0000;
        endcase
    end

endmodule

verilog/regfile.v
// regfile.v
// 32 x 32-bit register file
// - 2 read ports (combinational)
// - 1 write port (sequential)
// - r0 is hardwired to 0

module regfile (
    input  wire        clk,
    input  wire        reset,

    // write port
    input  wire        we,          // Write is enabled
    input  wire [4:0]  rd_addr,     // Register to write to (rd)
    input  wire [31:0] rd_data,     // Data to write

    // read port 1
    input  wire [4:0]  rs_addr,      // Register to read from (rs)
    output wire [31:0] rs_data,      // Data read

    // read port 2
    input  wire [4:0]  rt_addr,      // Register to read from (rt)
    output wire [31:0] rt_data,      // Data read

    output wire [31:0] debug_r1
);

    reg [31:0] regs [31:0];
    integer i;

    always @(posedge clk) begin
        if (reset) begin
            // On a high reset, we clear all registers to 0
            for (i = 0; i < 32; i = i + 1) begin
                regs[i] <= 32'h0000_0000;
            end
        end else begin
            // If we need to write, and the address is not r0, then write
            if (we && (rd_addr != 5'd0)) begin
                regs[rd_addr] <= rd_data;
            end
        end
    end

    // Combinatorial read port. Will update immediately without waiting for clock edge
    assign rs_data = (rs_addr == 5'd0) ? 32'h0000_0000 : regs[rs_addr];
    assign rt_data = (rt_addr == 5'd0) ? 32'h0000_0000 : regs[rt_addr];

    assign debug_r1 = regs[1];  // We use this for debugging

endmodule

verilog/instr_rom.v
// instr_rom.v
// Simple instruction ROM, word addressed

module instr_rom (
    input  wire [9:0]   addr,   // word address (not byte)
    output reg  [31:0]  data
);

    // Tiny program:
    // 0: ADDI r1, r1, 1
    // 1: ADDI r2, r2, 2
    // 2: J    0
    //
    // So r1,r2 increments forever.

    // helper function to build I-type (ADDI-style) instructions
    function [31:0] mk_addi;
        input [4:0] rd;
        input [4:0] rs;
        input [15:0] imm;
        begin
            mk_addi = {6'h10, rd, rs, imm}; // opcode 0x10
        end
    endfunction

    function [31:0] mk_j;
        input [25:0] imm26;
        begin
            mk_j = {6'h28, imm26}; // opcode 0x28
        end
    endfunction

    always @* begin
        case (addr)
            10'd0: data = mk_addi(5'd1, 5'd1, 16'd1);      // ADDI r1, r1, 1
            10'd1: data = mk_addi(5'd2, 5'd2, 16'd2);      // ADDI r2, r2, 2
            10'd2: data = mk_j(26'd0);                     // J 0
            default: data = 32'h00000000;                  // NOP
        endcase
    end

endmodule

verilog/cpu_core.v
// cpu_core.v
// Minimal single-cycle Nova-like core:
// - PC
// - regfile
// - ALU
// - instruction ROM
// No RAM, no loads/stores yet.

module cpu_core (
    input  wire        clk,         // We have a clock input
    input  wire        reset,       // We have a reset input

    output reg  [31:0] pc,         // expose PC for debug
    output wire [31:0] reg1_value  // expose r1 for debug/LED
);

    // === Instruction ROM ===

    wire [31:0] instr;

    // word address = pc[11:2] (assuming 4-byte instructions)
    instr_rom rom (
        .addr(pc[11:2]),
        .data(instr)
    );

    // === Decode ===

    wire [5:0]  opcode = instr[31:26];      // 6 bits opcode
    wire [4:0]  rd     = instr[25:21];      // 5 bit destination register
    wire [4:0]  rs     = instr[20:16];      // 5 bit source register
    wire [4:0]  rt     = instr[15:11];      // 5 bit target register
    wire [15:0] imm16  = instr[15:0];       // This is an overlap with the bits in RT, we can't use RT AND imm16 at the same time
    wire [25:0] target = instr[25:0];       // 26bit target for J-type

    // sign-extend imm16
    wire [31:0] imm_sext = {{16{imm16[15]}}, imm16};        // extend 11 bit immediate to 32 bits

    // Opcodes
    localparam OP_ADD  = 6'h00;
    localparam OP_SUB  = 6'h01;
    localparam OP_AND  = 6'h02;
    localparam OP_OR   = 6'h03;
    localparam OP_XOR  = 6'h04;
    localparam OP_ADDI = 6'h10;
    localparam OP_J    = 6'h28;

    // === Register file ===

    wire [31:0] rs_val;
    wire [31:0] rt_val;

    reg         rd_we;
    reg  [4:0]  rd_addr;
    reg  [31:0] rd_data;

    regfile rf (
        .clk    (clk),          // Clock pulse
        .reset  (reset),        // Reset input
        .we     (rd_we),        // Write enabled
        .rd_addr  (rd_addr),    // Register of destination
        .rd_data  (rd_data),
        .rs_addr (rs),          // Register of source
        .rs_data (rs_val),
        .rt_addr (rt),          // Register of target
        .rt_data (rt_val),
        .debug_r1 (reg1_value)  // Debug for r1
    );

    // === ALU ===

    reg  [5:0]  alu_op;
    wire [31:0] alu_rd;

    // This connects the ALU
    alu the_alu (
        .alu_op  (alu_op),
        .rs      (rs_val),
        .rt      (rt_val),
        .imm16   (imm16),
        .target  (target),
        .rd      (alu_rd)
    );

    // === Next PC logic & control ===

    reg [31:0] next_pc;

    always @* begin
        // Default values
        rd_we    = 1'b0;
        rd_addr = 5'd0;
        rd_data = 32'h0000_0000;
        alu_op   = 6'h3E;
        next_pc  = pc + 32'd4;

        case (opcode)
            OP_ADD: begin
                alu_op   = 6'h0;       // ALU_ADD
                rd_we    = 1'b1;       // write enabled
                rd_addr = rd;          // rd is the destination
                rd_data = alu_rd;      // Data is alu_rd result
            end

            OP_ADDI: begin
                alu_op   = 6'h10;      // ALU_ADDI
                rd_we    = 1'b1;       // write enabled
                rd_addr = rd;          // rd is the destination
                rd_data = alu_rd;      // data is alu_rd
            end

            OP_J: begin
                // Jump to current PC (last 3 bits), plus target shifted left 2
                next_pc = {pc[31:28], target, 2'b00};
            end

            default: begin
                // unimplemented opcodes => NOP
            end
        endcase
    end

    // PC register
    always @(posedge clk) begin
        if (reset) begin
            pc <= 32'h0000_0000;
        end else begin
            pc <= next_pc;
        end
    end

endmodule

verilog/cpu_core_tb.v
`timescale 1ns/1ps

module cpu_core_tb;
  reg clk;
  reg reset;

  cpu_core uut (
      .clk(clk),
      .reset(reset)
  );

  initial begin
    clk = 0;
    forever #5 clk = ~clk;
  end

  initial begin

    $monitor("Time=%0t clk=%b reset=%b alu_op=%d rd=%h", $time, clk, reset, uut.alu_op, uut.alu_rd);
    $dumpfile("cpu_core.vcd");
    $dumpvars(0, cpu_core_tb);

    reset = 1;
    #20;
    reset = 0;

    #1000;

    $display("Test completed");
    $finish;
  end
endmodule

verilog/cpu_core.vcd
$date
	Wed Nov 19 12:37:01 2025
$end
$version
	Icarus Verilog
$end
$timescale
	1ps
$end
$scope module cpu_core_tb $end
$var reg 1 ! clk $end
$var reg 1 " reset $end
$scope module uut $end
$var wire 1 ! clk $end
$var wire 1 " reset $end
$var wire 26 # target [25:0] $end
$var wire 32 $ rt_val [31:0] $end
$var wire 5 % rt [4:0] $end
$var wire 32 & rs_val [31:0] $end
$var wire 5 ' rs [4:0] $end
$var wire 32 ( reg1_value [31:0] $end
$var wire 5 ) rd [4:0] $end
$var wire 6 * opcode [5:0] $end
$var wire 32 + instr [31:0] $end
$var wire 32 , imm_sext [31:0] $end
$var wire 16 - imm16 [15:0] $end
$var wire 32 . alu_rd [31:0] $end
$var parameter 6 / OP_ADD $end
$var parameter 6 0 OP_ADDI $end
$var parameter 6 1 OP_AND $end
$var parameter 6 2 OP_J $end
$var parameter 6 3 OP_OR $end
$var parameter 6 4 OP_SUB $end
$var parameter 6 5 OP_XOR $end
$var reg 6 6 alu_op [5:0] $end
$var reg 32 7 next_pc [31:0] $end
$var reg 32 8 pc [31:0] $end
$var reg 5 9 rd_addr [4:0] $end
$var reg 32 : rd_data [31:0] $end
$var reg 1 ; rd_we $end
$scope module rf $end
$var wire 1 ! clk $end
$var wire 32 < debug_r1 [31:0] $end
$var wire 5 = rd_addr [4:0] $end
$var wire 32 > rd_data [31:0] $end
$var wire 1 " reset $end
$var wire 5 ? rs_addr [4:0] $end
$var wire 5 @ rt_addr [4:0] $end
$var wire 1 ; we $end
$var wire 32 A rt_data [31:0] $end
$var wire 32 B rs_data [31:0] $end
$var integer 32 C i [31:0] $end
$upscope $end
$scope module rom $end
$var wire 10 D addr [9:0] $end
$var reg 32 E data [31:0] $end
$scope function mk_addi $end
$var reg 16 F imm [15:0] $end
$var reg 5 G rd [4:0] $end
$var reg 5 H rs [4:0] $end
$upscope $end
$scope function mk_j $end
$var reg 26 I imm26 [25:0] $end
$upscope $end
$upscope $end
$scope module the_alu $end
$var wire 6 J alu_op [5:0] $end
$var wire 16 K imm16 [15:0] $end
$var wire 32 L rs [31:0] $end
$var wire 32 M rt [31:0] $end
$var wire 26 N target [25:0] $end
$var parameter 6 O ALU_ADD $end
$var parameter 6 P ALU_ADDI $end
$var parameter 6 Q ALU_AND $end
$var parameter 6 R ALU_OR $end
$var parameter 6 S ALU_SUB $end
$var parameter 6 T ALU_XOR $end
$var reg 32 U rd [31:0] $end
$upscope $end
$upscope $end
$upscope $end
$enddefinitions $end
$comment Show the parameter values. $end
$dumpall
b100 T
b1 S
b11 R
b10 Q
b10000 P
b0 O
b100 5
b1 4
b11 3
b101000 2
b10 1
b10000 0
b0 /
$end
#0
$dumpvars
bx U
bx N
bx M
bx L
bx K
bx J
bx I
bx H
bx G
bx F
bx E
bx D
bx C
bx B
bx A
bx @
bx ?
bx >
bx =
bx <
x;
bx :
bx 9
bx 8
bx 7
bx 6
bx .
bx -
bx ,
bx +
bx *
bx )
bx (
bx '
bx &
bx %
bx $
bx #
1"
0!
$end
#5000
b0 $
b0 A
b0 M
b0 &
b0 B
b0 L
b1000010000000000000001 #
b1000010000000000000001 N
b1 ,
b1 -
b1 K
b0 %
b0 @
b1 '
b1 ?
b1 )
b10000 *
b1 .
b1 U
b1000000001000010000000000000001 +
b1000000001000010000000000000001 E
b1 G
b1 H
b1 F
b100 7
b10000 6
b10000 J
b1 :
b1 >
b1 9
b1 =
1;
b0 D
b0 (
b0 <
b0 8
b100000 C
1!
#10000
0!
#15000
b100000 C
1!
#20000
0!
0"
#25000
b10000100000000000000010 #
b10000100000000000000010 N
b10 ,
b10 -
b10 K
b10 '
b10 ?
b10 )
b10 .
b10 U
b1000000010000100000000000000010 +
b1000000010000100000000000000010 E
b10 G
b10 H
b10 F
b0 &
b0 B
b0 L
b1000 7
b10000 6
b10000 J
b10 :
b10 >
b10 9
b10 =
1;
b1 D
b1 (
b1 <
b100 8
1!
#30000
0!
#35000
b0 #
b0 N
b0 ,
b0 -
b0 K
b0 '
b0 ?
b0 )
b101000 *
b10100000000000000000000000000000 +
b10100000000000000000000000000000 E
b0 I
b0 .
b0 U
b0 7
b111110 6
b111110 J
b0 :
b0 >
b0 9
b0 =
0;
b10 D
b0 &
b0 B
b0 L
b1000 8
1!
#40000
0!
#45000
b10 :
b10 >
b10 .
b10 U
b1 &
b1 B
b1 L
b1 9
b1 =
1;
b10000 6
b10000 J
b1000010000000000000001 #
b1000010000000000000001 N
b1 ,
b1 -
b1 K
b1 '
b1 ?
b1 )
b10000 *
b1000000001000010000000000000001 +
b1000000001000010000000000000001 E
b1 G
b1 H
b1 F
b100 7
b0 D
b0 8
1!
#50000
0!
#55000
b10000100000000000000010 #
b10000100000000000000010 N
b10 ,
b10 -
b10 K
b10 '
b10 ?
b10 )
b1000000010000100000000000000010 +
b1000000010000100000000000000010 E
b10 G
b10 H
b10 F
b100 .
b100 U
b1000 7
b10000 6
b10000 J
b100 :
b100 >
b10 9
b10 =
1;
b1 D
b10 &
b10 B
b10 L
b100 8
b10 (
b10 <
1!
#60000
0!
#65000
b0 #
b0 N
b0 ,
b0 -
b0 K
b0 '
b0 ?
b0 )
b101000 *
b0 .
b0 U
b10100000000000000000000000000000 +
b10100000000000000000000000000000 E
b0 &
b0 B
b0 L
b0 7
b111110 6
b111110 J
b0 :
b0 >
b0 9
b0 =
0;
b10 D
b1000 8
1!
#70000
0!
#75000
b11 :
b11 >
b11 .
b11 U
b10 &
b10 B
b10 L
b1 9
b1 =
1;
b10000 6
b10000 J
b1000010000000000000001 #
b1000010000000000000001 N
b1 ,
b1 -
b1 K
b1 '
b1 ?
b1 )
b10000 *
b1000000001000010000000000000001 +
b1000000001000010000000000000001 E
b1 G
b1 H
b1 F
b100 7
b0 D
b0 8
1!
#80000
0!
#85000
b10000100000000000000010 #
b10000100000000000000010 N
b10 ,
b10 -
b10 K
b10 '
b10 ?
b10 )
b110 .
b110 U
b1000000010000100000000000000010 +
b1000000010000100000000000000010 E
b10 G
b10 H
b10 F
b100 &
b100 B
b100 L
b1000 7
b10000 6
b10000 J
b110 :
b110 >
b10 9
b10 =
1;
b1 D
b11 (
b11 <
b100 8
1!
#90000
0!
#95000
b0 #
b0 N
b0 ,
b0 -
b0 K
b0 '
b0 ?
b0 )
b101000 *
b10100000000000000000000000000000 +
b10100000000000000000000000000000 E
b0 .
b0 U
b0 7
b111110 6
b111110 J
b0 :
b0 >
b0 9
b0 =
0;
b10 D
b0 &
b0 B
b0 L
b1000 8
1!
#100000
0!
#105000
b100 :
b100 >
b100 .
b100 U
b11 &
b11 B
b11 L
b1 9
b1 =
1;
b10000 6
b10000 J
b1000010000000000000001 #
b1000010000000000000001 N
b1 ,
b1 -
b1 K
b1 '
b1 ?
b1 )
b10000 *
b1000000001000010000000000000001 +
b1000000001000010000000000000001 E
b1 G
b1 H
b1 F
b100 7
b0 D
b0 8
1!
#110000
0!
#115000
b10000100000000000000010 #
b10000100000000000000010 N
b10 ,
b10 -
b10 K
b10 '
b10 ?
b10 )
b1000000010000100000000000000010 +
b1000000010000100000000000000010 E
b10 G
b10 H
b10 F
b1000 .
b1000 U
b1000 7
b10000 6
b10000 J
b1000 :
b1000 >
b10 9
b10 =
1;
b1 D
b110 &
b110 B
b110 L
b100 8
b100 (
b100 <
1!
#120000
0!
#125000
b0 #
b0 N
b0 ,
b0 -
b0 K
b0 '
b0 ?
b0 )
b101000 *
b0 .
b0 U
b10100000000000000000000000000000 +
b10100000000000000000000000000000 E
b0 &
b0 B
b0 L
b0 7
b111110 6
b111110 J
b0 :
b0 >
b0 9
b0 =
0;
b10 D
b1000 8
1!
#130000
0!
#135000
b101 :
b101 >
b101 .
b101 U
b100 &
b100 B
b100 L
b1 9
b1 =
1;
b10000 6
b10000 J
b1000010000000000000001 #
b1000010000000000000001 N
b1 ,
b1 -
b1 K
b1 '
b1 ?
b1 )
b10000 *
b1000000001000010000000000000001 +
b1000000001000010000000000000001 E
b1 G
b1 H
b1 F
b100 7
b0 D
b0 8
1!
#140000
0!
#145000
b10000100000000000000010 #
b10000100000000000000010 N
b10 ,
b10 -
b10 K
b10 '
b10 ?
b10 )
b1010 .
b1010 U
b1000000010000100000000000000010 +
b1000000010000100000000000000010 E
b10 G
b10 H
b10 F
b1000 &
b1000 B
b1000 L
b1000 7
b10000 6
b10000 J
b1010 :
b1010 >
b10 9
b10 =
1;
b1 D
b101 (
b101 <
b100 8
1!
#150000
0!
#155000
b0 #
b0 N
b0 ,
b0 -
b0 K
b0 '
b0 ?
b0 )
b101000 *
b10100000000000000000000000000000 +
b10100000000000000000000000000000 E
b0 .
b0 U
b0 7
b111110 6
b111110 J
b0 :
b0 >
b0 9
b0 =
0;
b10 D
b0 &
b0 B
b0 L
b1000 8
1!
#160000
0!
#165000
b110 :
b110 >
b110 .
b110 U
b101 &
b101 B
b101 L
b1 9
b1 =
1;
b10000 6
b10000 J
b1000010000000000000001 #
b1000010000000000000001 N
b1 ,
b1 -
b1 K
b1 '
b1 ?
b1 )
b10000 *
b1000000001000010000000000000001 +
b1000000001000010000000000000001 E
b1 G
b1 H
b1 F
b100 7
b0 D
b0 8
1!
#170000
0!
#175000
b10000100000000000000010 #
b10000100000000000000010 N
b10 ,
b10 -
b10 K
b10 '
b10 ?
b10 )
b1000000010000100000000000000010 +
b1000000010000100000000000000010 E
b10 G
b10 H
b10 F
b1100 .
b1100 U
b1000 7
b10000 6
b10000 J
b1100 :
b1100 >
b10 9
b10 =
1;
b1 D
b1010 &
b1010 B
b1010 L
b100 8
b110 (
b110 <
1!
#180000
0!
#185000
b0 #
b0 N
b0 ,
b0 -
b0 K
b0 '
b0 ?
b0 )
b101000 *
b0 .
b0 U
b10100000000000000000000000000000 +
b10100000000000000000000000000000 E
b0 &
b0 B
b0 L
b0 7
b111110 6
b111110 J
b0 :
b0 >
b0 9
b0 =
0;
b10 D
b1000 8
1!
#190000
0!
#195000
b111 :
b111 >
b111 .
b111 U
b110 &
b110 B
b110 L
b1 9
b1 =
1;
b10000 6
b10000 J
b1000010000000000000001 #
b1000010000000000000001 N
b1 ,
b1 -
b1 K
b1 '
b1 ?
b1 )
b10000 *
b1000000001000010000000000000001 +
b1000000001000010000000000000001 E
b1 G
b1 H
b1 F
b100 7
b0 D
b0 8
1!
#200000
0!
#205000
b10000100000000000000010 #
b10000100000000000000010 N
b10 ,
b10 -
b10 K
b10 '
b10 ?
b10 )
b1110 .
b1110 U
b1000000010000100000000000000010 +
b1000000010000100000000000000010 E
b10 G
b10 H
b10 F
b1100 &
b1100 B
b1100 L
b1000 7
b10000 6
b10000 J
b1110 :
b1110 >
b10 9
b10 =
1;
b1 D
b111 (
b111 <
b100 8
1!
#210000
0!
#215000
b0 #
b0 N
b0 ,
b0 -
b0 K
b0 '
b0 ?
b0 )
b101000 *
b10100000000000000000000000000000 +
b10100000000000000000000000000000 E
b0 .
b0 U
b0 7
b111110 6
b111110 J
b0 :
b0 >
b0 9
b0 =
0;
b10 D
b0 &
b0 B
b0 L
b1000 8
1!
#220000
0!
#225000
b1000 :
b1000 >
b1000 .
b1000 U
b111 &
b111 B
b111 L
b1 9
b1 =
1;
b10000 6
b10000 J
b1000010000000000000001 #
b1000010000000000000001 N
b1 ,
b1 -
b1 K
b1 '
b1 ?
b1 )
b10000 *
b1000000001000010000000000000001 +
b1000000001000010000000000000001 E
b1 G
b1 H
b1 F
b100 7
b0 D
b0 8
1!
#230000
0!
#235000
b10000100000000000000010 #
b10000100000000000000010 N
b10 ,
b10 -
b10 K
b10 '
b10 ?
b10 )
b1000000010000100000000000000010 +
b1000000010000100000000000000010 E
b10 G
b10 H
b10 F
b10000 .
b10000 U
b1000 7
b10000 6
b10000 J
b10000 :
b10000 >
b10 9
b10 =
1;
b1 D
b1110 &
b1110 B
b1110 L
b100 8
b1000 (
b1000 <
1!
#240000
0!
#245000
b0 #
b0 N
b0 ,
b0 -
b0 K
b0 '
b0 ?
b0 )
b101000 *
b0 .
b0 U
b10100000000000000000000000000000 +
b10100000000000000000000000000000 E
b0 &
b0 B
b0 L
b0 7
b111110 6
b111110 J
b0 :
b0 >
b0 9
b0 =
0;
b10 D
b1000 8
1!
#250000
0!
#255000
b1001 :
b1001 >
b1001 .
b1001 U
b1000 &
b1000 B
b1000 L
b1 9
b1 =
1;
b10000 6
b10000 J
b1000010000000000000001 #
b1000010000000000000001 N
b1 ,
b1 -
b1 K
b1 '
b1 ?
b1 )
b10000 *
b1000000001000010000000000000001 +
b1000000001000010000000000000001 E
b1 G
b1 H
b1 F
b100 7
b0 D
b0 8
1!
#260000
0!
#265000
b10000100000000000000010 #
b10000100000000000000010 N
b10 ,
b10 -
b10 K
b10 '
b10 ?
b10 )
b10010 .
b10010 U
b1000000010000100000000000000010 +
b1000000010000100000000000000010 E
b10 G
b10 H
b10 F
b10000 &
b10000 B
b10000 L
b1000 7
b10000 6
b10000 J
b10010 :
b10010 >
b10 9
b10 =
1;
b1 D
b1001 (
b1001 <
b100 8
1!
#270000
0!
#275000
b0 #
b0 N
b0 ,
b0 -
b0 K
b0 '
b0 ?
b0 )
b101000 *
b10100000000000000000000000000000 +
b10100000000000000000000000000000 E
b0 .
b0 U
b0 7
b111110 6
b111110 J
b0 :
b0 >
b0 9
b0 =
0;
b10 D
b0 &
b0 B
b0 L
b1000 8
1!
#280000
0!
#285000
b1010 :
b1010 >
b1010 .
b1010 U
b1001 &
b1001 B
b1001 L
b1 9
b1 =
1;
b10000 6
b10000 J
b1000010000000000000001 #
b1000010000000000000001 N
b1 ,
b1 -
b1 K
b1 '
b1 ?
b1 )
b10000 *
b1000000001000010000000000000001 +
b1000000001000010000000000000001 E
b1 G
b1 H
b1 F
b100 7
b0 D
b0 8
1!
#290000
0!
#295000
b10000100000000000000010 #
b10000100000000000000010 N
b10 ,
b10 -
b10 K
b10 '
b10 ?
b10 )
b1000000010000100000000000000010 +
b1000000010000100000000000000010 E
b10 G
b10 H
b10 F
b10100 .
b10100 U
b1000 7
b10000 6
b10000 J
b10100 :
b10100 >
b10 9
b10 =
1;
b1 D
b10010 &
b10010 B
b10010 L
b100 8
b1010 (
b1010 <
1!
#300000
0!
#305000
b0 #
b0 N
b0 ,
b0 -
b0 K
b0 '
b0 ?
b0 )
b101000 *
b0 .
b0 U
b10100000000000000000000000000000 +
b10100000000000000000000000000000 E
b0 &
b0 B
b0 L
b0 7
b111110 6
b111110 J
b0 :
b0 >
b0 9
b0 =
0;
b10 D
b1000 8
1!
#310000
0!
#315000
b1011 :
b1011 >
b1011 .
b1011 U
b1010 &
b1010 B
b1010 L
b1 9
b1 =
1;
b10000 6
b10000 J
b1000010000000000000001 #
b1000010000000000000001 N
b1 ,
b1 -
b1 K
b1 '
b1 ?
b1 )
b10000 *
b1000000001000010000000000000001 +
b1000000001000010000000000000001 E
b1 G
b1 H
b1 F
b100 7
b0 D
b0 8
1!
#320000
0!
#325000
b10000100000000000000010 #
b10000100000000000000010 N
b10 ,
b10 -
b10 K
b10 '
b10 ?
b10 )
b10110 .
b10110 U
b1000000010000100000000000000010 +
b1000000010000100000000000000010 E
b10 G
b10 H
b10 F
b10100 &
b10100 B
b10100 L
b1000 7
b10000 6
b10000 J
b10110 :
b10110 >
b10 9
b10 =
1;
b1 D
b1011 (
b1011 <
b100 8
1!
#330000
0!
#335000
b0 #
b0 N
b0 ,
b0 -
b0 K
b0 '
b0 ?
b0 )
b101000 *
b10100000000000000000000000000000 +
b10100000000000000000000000000000 E
b0 .
b0 U
b0 7
b111110 6
b111110 J
b0 :
b0 >
b0 9
b0 =
0;
b10 D
b0 &
b0 B
b0 L
b1000 8
1!
#340000
0!
#345000
b1100 :
b1100 >
b1100 .
b1100 U
b1011 &
b1011 B
b1011 L
b1 9
b1 =
1;
b10000 6
b10000 J
b1000010000000000000001 #
b1000010000000000000001 N
b1 ,
b1 -
b1 K
b1 '
b1 ?
b1 )
b10000 *
b1000000001000010000000000000001 +
b1000000001000010000000000000001 E
b1 G
b1 H
b1 F
b100 7
b0 D
b0 8
1!
#350000
0!
#355000
b10000100000000000000010 #
b10000100000000000000010 N
b10 ,
b10 -
b10 K
b10 '
b10 ?
b10 )
b1000000010000100000000000000010 +
b1000000010000100000000000000010 E
b10 G
b10 H
b10 F
b11000 .
b11000 U
b1000 7
b10000 6
b10000 J
b11000 :
b11000 >
b10 9
b10 =
1;
b1 D
b10110 &
b10110 B
b10110 L
b100 8
b1100 (
b1100 <
1!
#360000
0!
#365000
b0 #
b0 N
b0 ,
b0 -
b0 K
b0 '
b0 ?
b0 )
b101000 *
b0 .
b0 U
b10100000000000000000000000000000 +
b10100000000000000000000000000000 E
b0 &
b0 B
b0 L
b0 7
b111110 6
b111110 J
b0 :
b0 >
b0 9
b0 =
0;
b10 D
b1000 8
1!
#370000
0!
#375000
b1101 :
b1101 >
b1101 .
b1101 U
b1100 &
b1100 B
b1100 L
b1 9
b1 =
1;
b10000 6
b10000 J
b1000010000000000000001 #
b1000010000000000000001 N
b1 ,
b1 -
b1 K
b1 '
b1 ?
b1 )
b10000 *
b1000000001000010000000000000001 +
b1000000001000010000000000000001 E
b1 G
b1 H
b1 F
b100 7
b0 D
b0 8
1!
#380000
0!
#385000
b10000100000000000000010 #
b10000100000000000000010 N
b10 ,
b10 -
b10 K
b10 '
b10 ?
b10 )
b11010 .
b11010 U
b1000000010000100000000000000010 +
b1000000010000100000000000000010 E
b10 G
b10 H
b10 F
b11000 &
b11000 B
b11000 L
b1000 7
b10000 6
b10000 J
b11010 :
b11010 >
b10 9
b10 =
1;
b1 D
b1101 (
b1101 <
b100 8
1!
#390000
0!
#395000
b0 #
b0 N
b0 ,
b0 -
b0 K
b0 '
b0 ?
b0 )
b101000 *
b10100000000000000000000000000000 +
b10100000000000000000000000000000 E
b0 .
b0 U
b0 7
b111110 6
b111110 J
b0 :
b0 >
b0 9
b0 =
0;
b10 D
b0 &
b0 B
b0 L
b1000 8
1!
#400000
0!
#405000
b1110 :
b1110 >
b1110 .
b1110 U
b1101 &
b1101 B
b1101 L
b1 9
b1 =
1;
b10000 6
b10000 J
b1000010000000000000001 #
b1000010000000000000001 N
b1 ,
b1 -
b1 K
b1 '
b1 ?
b1 )
b10000 *
b1000000001000010000000000000001 +
b1000000001000010000000000000001 E
b1 G
b1 H
b1 F
b100 7
b0 D
b0 8
1!
#410000
0!
#415000
b10000100000000000000010 #
b10000100000000000000010 N
b10 ,
b10 -
b10 K
b10 '
b10 ?
b10 )
b1000000010000100000000000000010 +
b1000000010000100000000000000010 E
b10 G
b10 H
b10 F
b11100 .
b11100 U
b1000 7
b10000 6
b10000 J
b11100 :
b11100 >
b10 9
b10 =
1;
b1 D
b11010 &
b11010 B
b11010 L
b100 8
b1110 (
b1110 <
1!
#420000
0!
#425000
b0 #
b0 N
b0 ,
b0 -
b0 K
b0 '
b0 ?
b0 )
b101000 *
b0 .
b0 U
b10100000000000000000000000000000 +
b10100000000000000000000000000000 E
b0 &
b0 B
b0 L
b0 7
b111110 6
b111110 J
b0 :
b0 >
b0 9
b0 =
0;
b10 D
b1000 8
1!
#430000
0!
#435000
b1111 :
b1111 >
b1111 .
b1111 U
b1110 &
b1110 B
b1110 L
b1 9
b1 =
1;
b10000 6
b10000 J
b1000010000000000000001 #
b1000010000000000000001 N
b1 ,
b1 -
b1 K
b1 '
b1 ?
b1 )
b10000 *
b1000000001000010000000000000001 +
b1000000001000010000000000000001 E
b1 G
b1 H
b1 F
b100 7
b0 D
b0 8
1!
#440000
0!
#445000
b10000100000000000000010 #
b10000100000000000000010 N
b10 ,
b10 -
b10 K
b10 '
b10 ?
b10 )
b11110 .
b11110 U
b1000000010000100000000000000010 +
b1000000010000100000000000000010 E
b10 G
b10 H
b10 F
b11100 &
b11100 B
b11100 L
b1000 7
b10000 6
b10000 J
b11110 :
b11110 >
b10 9
b10 =
1;
b1 D
b1111 (
b1111 <
b100 8
1!
#450000
0!
#455000
b0 #
b0 N
b0 ,
b0 -
b0 K
b0 '
b0 ?
b0 )
b101000 *
b10100000000000000000000000000000 +
b10100000000000000000000000000000 E
b0 .
b0 U
b0 7
b111110 6
b111110 J
b0 :
b0 >
b0 9
b0 =
0;
b10 D
b0 &
b0 B
b0 L
b1000 8
1!
#460000
0!
#465000
b10000 :
b10000 >
b10000 .
b10000 U
b1111 &
b1111 B
b1111 L
b1 9
b1 =
1;
b10000 6
b10000 J
b1000010000000000000001 #
b1000010000000000000001 N
b1 ,
b1 -
b1 K
b1 '
b1 ?
b1 )
b10000 *
b1000000001000010000000000000001 +
b1000000001000010000000000000001 E
b1 G
b1 H
b1 F
b100 7
b0 D
b0 8
1!
#470000
0!
#475000
b10000100000000000000010 #
b10000100000000000000010 N
b10 ,
b10 -
b10 K
b10 '
b10 ?
b10 )
b1000000010000100000000000000010 +
b1000000010000100000000000000010 E
b10 G
b10 H
b10 F
b100000 .
b100000 U
b1000 7
b10000 6
b10000 J
b100000 :
b100000 >
b10 9
b10 =
1;
b1 D
b11110 &
b11110 B
b11110 L
b100 8
b10000 (
b10000 <
1!
#480000
0!
#485000
b0 #
b0 N
b0 ,
b0 -
b0 K
b0 '
b0 ?
b0 )
b101000 *
b0 .
b0 U
b10100000000000000000000000000000 +
b10100000000000000000000000000000 E
b0 &
b0 B
b0 L
b0 7
b111110 6
b111110 J
b0 :
b0 >
b0 9
b0 =
0;
b10 D
b1000 8
1!
#490000
0!
#495000
b10001 :
b10001 >
b10001 .
b10001 U
b10000 &
b10000 B
b10000 L
b1 9
b1 =
1;
b10000 6
b10000 J
b1000010000000000000001 #
b1000010000000000000001 N
b1 ,
b1 -
b1 K
b1 '
b1 ?
b1 )
b10000 *
b1000000001000010000000000000001 +
b1000000001000010000000000000001 E
b1 G
b1 H
b1 F
b100 7
b0 D
b0 8
1!
#500000
0!
#505000
b10000100000000000000010 #
b10000100000000000000010 N
b10 ,
b10 -
b10 K
b10 '
b10 ?
b10 )
b100010 .
b100010 U
b1000000010000100000000000000010 +
b1000000010000100000000000000010 E
b10 G
b10 H
b10 F
b100000 &
b100000 B
b100000 L
b1000 7
b10000 6
b10000 J
b100010 :
b100010 >
b10 9
b10 =
1;
b1 D
b10001 (
b10001 <
b100 8
1!
#510000
0!
#515000
b0 #
b0 N
b0 ,
b0 -
b0 K
b0 '
b0 ?
b0 )
b101000 *
b10100000000000000000000000000000 +
b10100000000000000000000000000000 E
b0 .
b0 U
b0 7
b111110 6
b111110 J
b0 :
b0 >
b0 9
b0 =
0;
b10 D
b0 &
b0 B
b0 L
b1000 8
1!
#520000
0!
